Workbook

Sheet pr
A1: PR_ID | B1: Date | C1: Department | D1: Item | E1: Quantity | F1: Estimated Cost | G1: Approval Status
A2: PR001 | B2: 46025 | C2: IT | D2: Laptop | E2: 5 | F2: 50000 | G2: Approved
A3: PR002 | B3: 46056 | C3: HR | D3: Office Chairs | E3: 10 | F3: 3000 | G3: Approved
A4: PR003 | B4: 46084 | C4: Finance | D4: Printer | E4: 2 | F4: 15000 | G4: Pending
A5: PR004 | B5: 46115 | C5: Marketing | D5: Projector | E5: 1 | F5: 40000 | G5: Approved
A6: PR005 | B6: 46145 | C6: Admin | D6: Stationery Kit | E6: 20 | F6: 500 | G6: Approved

Sheet po
A1: PO_ID | B1: PR_ID | C1: Vendor Name | D1: Item | E1: Qty Ordered | F1: Price/Unit | G1: Total Cost | H1: Order Date
A2: PO001 | B2: PR001 | C2: TechSupplier Ltd | D2: Laptop | E2: 5 | F2: 48000 | G2: =E2*F2 -> 240000 | H2: 46056
A3: PO002 | B3: PR002 | C3: FurniCo | D3: Office Chairs | E3: 10 | F3: 2800 | G3: =E3*F3 -> 28000 | H3: 46084
A4: PO003 | B4: PR003 | C4: PrintWorld | D4: Printer | E4: 2 | F4: 14000 | G4: =E4*F4 -> 28000 | H4: 46115
A5: PO004 | B5: PR004 | C5: AV Solutions | D5: Projector | E5: 1 | F5: 38000 | G5: =E5*F5 -> 38000 | H5: 46145
A6: PO005 | B6: PR005 | C6: OfficeMart | D6: Stationery | E6: 20 | F6: 450 | G6: =E6*F6 -> 9000 | H6: 46176

Sheet grn
A1: GRN_ID | B1: PO_ID | C1: Quantity Received | D1: Quality Status | E1: Delivery Date
A2: GRN001 | B2: PO001 | C2: 5 | D2: Good | E2: 46145
A3: GRN002 | B3: PO002 | C3: 10 | D3: Good | E3: 46176
A4: GRN003 | B4: PO003 | C4: 1 | D4: Good | E4: 46206
A5: GRN004 | B5: PO004 | C5: 1 | D5: Damaged | E5: 46237
A6: GRN005 | B6: PO005 | C6: 20 | D6: Good | E6: 46268

Sheet Invoice
A1: Invoice_ID | B1: PO_ID | C1: Amount Billed | D1: Invoice Date | E1: Payment Status | F1: Payment Date | G1: Match Status | H1: Column1 | I1: Column2 | J1: Column3 | K1: Column4 | L1: Column5 | M1: Column6
A2: INV001 | B2: PO001 | C2: 240000 | D2: 46176 | E2: Paid | F2: 46298 | G2: =IF(AND( C2=VLOOKUP(B2,po!A:G,7,FALSE), VLOOKUP(B2,po!A:G,5,FALSE)=VLOOKUP(B2,grn!B:C,2,FALSE) ),"Match","Mismatch") -> Match | H2: =VLOOKUP(B2,po!A:H,7,FALSE) -> 240000 | I2: =IF(C2=H2, "ok", "notok") -> ok | J2: =VLOOKUP(Table4[[#This Row],[PO_ID]],po!A:G,5,FALSE) -> 5 | K2: =VLOOKUP(B2,grn!B:C,2,FALSE) -> 5 | L2: =IF(J2=K2,"OK","Not OK") -> OK | M2: =IF(AND(I2="OK",L2="OK"),"Match","Mismatch") -> Match
A3: INV002 | B3: PO002 | C3: 28000 | D3: 46206 | E3: Paid | F3: 46359 | G3: =IF(AND( C3=VLOOKUP(B3,po!A:G,7,FALSE), VLOOKUP(B3,po!A:G,5,FALSE)=VLOOKUP(B3,grn!B:C,2,FALSE) ),"Match","Mismatch") -> Match | H3: =VLOOKUP(B3,po!A:H,7,FALSE) -> 28000 | I3: =IF(C3=H3, "ok", "notok") -> ok | J3: =VLOOKUP(Table4[[#This Row],[PO_ID]],po!A:G,5,FALSE) -> 10 | K3: =VLOOKUP(B3,grn!B:C,2,FALSE) -> 10 | L3: =IF(J3=K3,"OK","Not OK") -> OK | M3: =IF(AND(I3="OK",L3="OK"),"Match","Mismatch") -> Match
A4: INV003 | B4: PO003 | C4: 28000 | D4: 46237 | E4: Pending | G4: =IF(AND( C4=VLOOKUP(B4,po!A:G,7,FALSE), VLOOKUP(B4,po!A:G,5,FALSE)=VLOOKUP(B4,grn!B:C,2,FALSE) ),"Match","Mismatch") -> Mismatch | H4: =VLOOKUP(B4,po!A:H,7,FALSE) -> 28000 | I4: =IF(C4=H4, "ok", "notok") -> ok | J4: =VLOOKUP(Table4[[#This Row],[PO_ID]],po!A:G,5,FALSE) -> 2 | K4: =VLOOKUP(B4,grn!B:C,2,FALSE) -> 1 | L4: =IF(J4=K4,"OK","Not OK") -> Not OK | M4: =IF(AND(I4="OK",L4="OK"),"Match","Mismatch") -> Mismatch
A5: INV004 | B5: PO004 | C5: 38000 | D5: 46268 | E5: Paid | F5: 15-03-2026 | G5: =IF(AND( C5=VLOOKUP(B5,po!A:G,7,FALSE), VLOOKUP(B5,po!A:G,5,FALSE)=VLOOKUP(B5,grn!B:C,2,FALSE) ),"Match","Mismatch") -> Match | H5: =VLOOKUP(B5,po!A:H,7,FALSE) -> 38000 | I5: =IF(C5=H5, "ok", "notok") -> ok | J5: =VLOOKUP(Table4[[#This Row],[PO_ID]],po!A:G,5,FALSE) -> 1 | K5: =VLOOKUP(B5,grn!B:C,2,FALSE) -> 1 | L5: =IF(J5=K5,"OK","Not OK") -> OK | M5: =IF(AND(I5="OK",L5="OK"),"Match","Mismatch") -> Match
A6: INV005 | B6: PO005 | C6: 9000 | D6: 46298 | E6: Paid | F6: 14-03-2026 | G6: =IF(AND( C6=VLOOKUP(B6,po!A:G,7,FALSE), VLOOKUP(B6,po!A:G,5,FALSE)=VLOOKUP(B6,grn!B:C,2,FALSE) ),"Match","Mismatch") -> Match | H6: =VLOOKUP(B6,po!A:H,7,FALSE) -> 9000 | I6: =IF(C6=H6, "ok", "notok") -> ok | J6: =VLOOKUP(Table4[[#This Row],[PO_ID]],po!A:G,5,FALSE) -> 20 | K6: =VLOOKUP(B6,grn!B:C,2,FALSE) -> 20 | L6: =IF(J6=K6,"OK","Not OK") -> OK | M6: =IF(AND(I6="OK",L6="OK"),"Match","Mismatch") -> Match

Sheet Sheet5
A1: PR_ID | B1: Date | C1: Department | D1: Item | E1: Quantity | F1: Estimated Cost | G1: Approval Status | H1: Column1
A2: PR001 | B2: 46025 | C2: IT | D2: Laptop | E2: 5 | F2: 50000 | G2: Approved
A3: PR002 | B3: 46056 | C3: HR | D3: Office Chairs | E3: 10 | F3: 3000 | G3: Approved | J3: PR
A4: PR003 | B4: 46084 | C4: Finance | D4: Printer | E4: 2 | F4: 15000 | G4: Pending | H4: PR
A5: PR004 | B5: 46115 | C5: Marketing | D5: Projector | E5: 1 | F5: 40000 | G5: Approved
A6: PR005 | B6: 46145 | C6: Admin | D6: Stationery Kit | E6: 20 | F6: 500 | G6: Approved
A9: PO_ID | B9: PR_ID | C9: Vendor Name | D9: Item | E9: Qty Ordered | F9: Price/Unit | G9: Total Cost | H9: Order Date
A10: PO001 | B10: PR001 | C10: TechSupplier Ltd | D10: Laptop | E10: 5 | F10: 48000 | G10: =E10*F10 -> 240000 | H10: 46056
A11: PO002 | B11: PR002 | C11: FurniCo | D11: Office Chairs | E11: 10 | F11: 2800 | G11: =E11*F11 -> 28000 | H11: 46084
A12: PO003 | B12: PR003 | C12: PrintWorld | D12: Printer | E12: 2 | F12: 14000 | G12: =E12*F12 -> 28000 | H12: 46115
A13: PO004 | B13: PR004 | C13: AV Solutions | D13: Projector | E13: 1 | F13: 38000 | G13: =E13*F13 -> 38000 | H13: 46145 | J13: PO
A14: PO005 | B14: PR005 | C14: OfficeMart | D14: Stationery | E14: 20 | F14: 450 | G14: =E14*F14 -> 9000 | H14: 46176
A17: GRN_ID | B17: PO_ID | C17: Quantity Received | D17: Quality Status | E17: Delivery Date | G17: grn
A18: GRN001 | B18: PO001 | C18: 5 | D18: Good | E18: 46145
A19: GRN002 | B19: PO002 | C19: 10 | D19: Good | E19: 46176
A20: GRN003 | B20: PO003 | C20: 1 | D20: Good | E20: 46206
A21: GRN004 | B21: PO004 | C21: 1 | D21: Damaged | E21: 46237
A22: GRN005 | B22: PO005 | C22: 20 | D22: Good | E22: 46268
A25: Invoice_ID | B25: PO_ID | C25: Amount Billed | D25: Invoice Date | E25: Payment Status | F25: Payment Date | G25: Match Status
A26: INV001 | B26: PO001 | C26: 240000 | D26: 46176 | E26: Paid | F26: 46298 | G26: =IF(AND( C26=VLOOKUP(B26,po!A:G,7,FALSE), VLOOKUP(B26,po!A:G,5,FALSE)=VLOOKUP(B26,grn!B:C,2,FALSE) ),"Match","Mismatch") -> Match
A27: INV002 | B27: PO002 | C27: 28000 | D27: 46206 | E27: Paid | F27: 46359 | G27: =IF(AND( C27=VLOOKUP(B27,po!A:G,7,FALSE), VLOOKUP(B27,po!A:G,5,FALSE)=VLOOKUP(B27,grn!B:C,2,FALSE) ),"Match","Mismatch") -> Match | J27: invoice
A28: INV003 | B28: PO003 | C28: 28000 | D28: 46237 | E28: Pending | G28: =IF(AND( C28=VLOOKUP(B28,po!A:G,7,FALSE), VLOOKUP(B28,po!A:G,5,FALSE)=VLOOKUP(B28,grn!B:C,2,FALSE) ),"Match","Mismatch") -> Mismatch
A29: INV004 | B29: PO004 | C29: 38000 | D29: 46268 | E29: Paid | F29: 15-03-2026 | G29: =IF(AND( C29=VLOOKUP(B29,po!A:G,7,FALSE), VLOOKUP(B29,po!A:G,5,FALSE)=VLOOKUP(B29,grn!B:C,2,FALSE) ),"Match","Mismatch") -> Match
A30: INV005 | B30: PO005 | C30: 9000 | D30: 46298 | E30: Paid | F30: 14-03-2026 | G30: =IF(AND( C30=VLOOKUP(B30,po!A:G,7,FALSE), VLOOKUP(B30,po!A:G,5,FALSE)=VLOOKUP(B30,grn!B:C,2,FALSE) ),"Match","Mismatch") -> Match
